string_to_ms/__init__.py
string_to_ms/ms.py
string_to_ms-0.0.5.dist-info/METADATA
string_to_ms-0.0.5.dist-info/WHEEL
string_to_ms-0.0.5.dist-info/licenses/LICENSE
string_to_ms-0.0.5.dist-info/RECORD
