Metadata-Version: 2.4
Name: string_to_ms
Version: 0.0.5
Summary: A package that converts string times into milliseconds and milliseconds back to readable strings
Author: chickenman34234
License-Expression: MIT
License-File: LICENSE
Classifier: Operating System :: OS Independent
Classifier: Programming Language :: Python :: 3
Requires-Python: >=3.9
